MANIFEST.in
README.md
pyproject.toml
setup.py
bigquery/src/grammar.json
bigquery/src/node-types.json
bigquery/src/parser.c
bigquery/src/scanner.cc
bigquery/src/tree_sitter/parser.h
bindings/python/__init__.py
jinja2/src/grammar.json
jinja2/src/node-types.json
jinja2/src/parser.c
jinja2/src/tree_sitter/parser.h
polysql.egg-info/PKG-INFO
polysql.egg-info/SOURCES.txt
polysql.egg-info/dependency_links.txt
polysql.egg-info/requires.txt
polysql.egg-info/top_level.txt
postgres/src/grammar.json
postgres/src/node-types.json
postgres/src/parser.c
postgres/src/scanner.cc
postgres/src/tree_sitter/parser.h