Metadata-Version: 2.1
Name: polysql
Version: 0.0.36
Summary: Grammar and parser used to parse SQL
